fortnitemasteuur/__init__.py
fortnitemasteuur/ftnlogin.py
fortnitemasteuur/ftnmcp.py
fortnite_masteur-0.1.6.dist-info/METADATA
fortnite_masteur-0.1.6.dist-info/WHEEL
fortnite_masteur-0.1.6.dist-info/top_level.txt
fortnite_masteur-0.1.6.dist-info/RECORD
