Metadata-Version: 2.1
Name: fortnite-masteur
Version: 0.1.6
Summary: is for manage ftn login and mcp
Home-page: https://github.com/baguettemanpy
Author: the baaguette man
Author-email: votre.email@example.com
Classifier: Programming Language :: Python :: 3
Classifier: License :: OSI Approved :: MIT License
Classifier: Operating System :: OS Independent
Requires-Python: >=3.12
Requires-Dist: requests
